dataPath/ALU.v
module ALU(
    input [31:0] srcA,
    input [31:0] srcB,
    input [2:0] ALUControl,
    output [31:0] res,
    output wire zero
);

reg [31:0] aux = 0;
reg aux_zero = 0;

always @(*)
begin
    case (ALUControl)
        3'b000:
            begin
                aux = srcA+srcB;
                aux_zero <= 0;
            end
        3'b001:
            begin
                aux = srcA-srcB;
                aux_zero <= 0;
            end
        3'b010:
            begin
                aux = srcA & srcB;
                aux_zero <= 0;
            end
        3'b011:
            begin
                aux = srcA | srcB;
                aux_zero <= 0;
            end
        3'b100:
            begin
                aux = (srcA == srcB);
                aux_zero <= srcA == srcB;
            end
        3'b101:
            begin
                aux = srcB > srcA;
                aux_zero <=  srcB > srcA;
            end
        default:
            begin
                aux = srcA;
                aux_zero <= 0;
            end
    endcase
end

assign zero = aux_zero;
assign res = aux;

endmodule

test/dp/alu_tb.v
`include "./dataPath/ALU.v"

module alu_tb;
    
    reg [31:0] srcA;
    reg [31:0] srcB;
    reg [2:0] ALUControl;
    wire [31:0] res;
    wire zero;

    ALU uut(
        .srcA(srcA),
        .srcB(srcB),
        .ALUControl(ALUControl),
        .res(res),
        .zero(zero)
    );

    initial begin
        $dumpfile("./waves/alu_tb.vcd");
        $dumpvars(0, alu_tb);

        srcA = 32'h00000003;
        srcB = 32'h00000001;
        
        // or  t0, s0, s1
        ALUControl = 3'b011;
        #10
        // and t1, s0, s1
        ALUControl = 3'b010;
        #10
        // odd t2, s0, s1
        ALUControl = 3'b000;
        #10
        // sub t3, s0, s1
        ALUControl = 3'b001;
        #10
        // sub t4, s1, s0
        srcA = 32'h00000001;
        srcB = 32'h00000003;
        ALUControl = 3'b001;
        #10
        // slt t5, s0, s1
        srcA = 32'h00000003;
        srcB = 32'h00000001;
        ALUControl = 3'b101;
        #10
        // slt t6, s1, s0
        ALUControl = 3'b101;
        srcA = 32'h00000001;
        srcB = 32'h00000003;
        #10
        // eq t6, s1, t4
        ALUControl = 3'b100;
        #10

        $finish;
    end

endmodule

waves/alu_tb.vcd
$date
	Thu Feb  8 16:35:58 2024
$end
$version
	Icarus Verilog
$end
$timescale
	1s
$end
$scope module alu_tb $end
$var wire 1 ! zero $end
$var wire 32 " res [31:0] $end
$var reg 3 # ALUControl [2:0] $end
$var reg 32 $ srcA [31:0] $end
$var reg 32 % srcB [31:0] $end
$scope module uut $end
$var wire 3 & ALUControl [2:0] $end
$var wire 32 ' res [31:0] $end
$var wire 32 ( srcA [31:0] $end
$var wire 32 ) srcB [31:0] $end
$var wire 1 ! zero $end
$var reg 32 * aux [31:0] $end
$var reg 1 + aux_zero $end
$upscope $end
$upscope $end
$enddefinitions $end
$comment Show the parameter values. $end
$dumpall
$end
#0
$dumpvars
0+
b11 *
b1 )
b11 (
b11 '
b11 &
b1 %
b11 $
b11 #
b11 "
0!
$end
#10
b1 "
b1 '
b1 *
b10 #
b10 &
#20
b100 "
b100 '
b100 *
b0 #
b0 &
#30
b10 "
b10 '
b10 *
b1 #
b1 &
#40
b11111111111111111111111111111110 "
b11111111111111111111111111111110 '
b11111111111111111111111111111110 *
b11 %
b11 )
b1 $
b1 (
#50
b0 "
b0 '
b0 *
b101 #
b101 &
b1 %
b1 )
b11 $
b11 (
#60
1!
1+
b1 "
b1 '
b1 *
b11 %
b11 )
b1 $
b1 (
#70
0!
0+
b0 "
b0 '
b0 *
b100 #
b100 &
